cpm_pytorch/CPM.py
cpm_pytorch/CPM_Image.py
cpm_pytorch/CPM_Map.py
cpm_pytorch/CPM_main.ipynb
cpm_pytorch/__init__.py
cpm_pytorch-0.1.0.dist-info/LICENSE
cpm_pytorch-0.1.0.dist-info/METADATA
cpm_pytorch-0.1.0.dist-info/WHEEL
cpm_pytorch-0.1.0.dist-info/RECORD
